procore/__init__.py
procore/exceptions.py
procore/procore.py
procore/apis/__init__.py
procore/apis/api_base.py
procore/apis/companies.py
procore/apis/projects.py
procore-0.1.0.dist-info/LICENSE
procore-0.1.0.dist-info/METADATA
procore-0.1.0.dist-info/WHEEL
procore-0.1.0.dist-info/top_level.txt
procore-0.1.0.dist-info/RECORD
