Metadata-Version: 2.1
Name: procore
Version: 0.1.0
Summary: Python SDK for accessing Procore APIs
Home-page: https://github.com/fylein/procore-sdk-py
Author: Shwetabh Kumar
Author-email: shwetabh.kumar@fyle.in
License: MIT
Keywords: procore,fyle,api,python,sdk
Platform: UNKNOWN
Classifier: Topic :: Internet :: WWW/HTTP
Classifier: Intended Audience :: Developers
Classifier: Programming Language :: Python :: 3
Classifier: License :: OSI Approved :: MIT License
Classifier: Operating System :: OS Independent
Requires-Dist: requests
